gmconfig/__init__.py
gmconfig/__main__.py
gmconfig/configuration.py
gmconfig/loaders/__init__.py
gmconfig/loaders/load.py
gmconfig/loaders/load_toml.py
gmconfig/loaders/load_yaml.py
gmconfig/utils/__init__.py
gmconfig/utils/basicimporter.py
gmconfig/utils/litemerge.py
gmconfig/utils/logger.py
gmconfig-0.4.0.dist-info/entry_points.txt
gmconfig-0.4.0.dist-info/LICENSE
gmconfig-0.4.0.dist-info/WHEEL
gmconfig-0.4.0.dist-info/METADATA
gmconfig-0.4.0.dist-info/RECORD
